vmanage_rest_session/__init__.py
vmanage_rest_session/internal_extension.py
vmanage_rest_session/vmanage_example.py
vmanage_rest_session/vmanage_session.py
vmanage_rest_session/api_data/administration_tenantManagementTenants_ResourceProfile_GET.log
vmanage_rest_session/api_data/administration_tenantManagementTenants_Tenants_GET.log
vmanage_rest_session/api_data/configuration_certificates_WANEdgeList_SendToControllers_status_GET_20.11.log
vmanage_rest_session/api_data/configuration_certificates_controllers_GET_20.11.log
vmanage_rest_session/api_data/configuration_devices_WANEdgeList_UploadWANEdgeList_POST_20.11.log
vmanage_rest_session/api_data/configuration_devices_WANEdgeList_UploadWANEdgeList_Payload_POST_20.11.log
vmanage_rest_session/api_data/configuration_devices_WANEdgeList_get_GET_20.11.log
vmanage_rest_session/api_data/configuration_devices_controller_get_GET_20.9.log
vmanage_rest_session/api_data/configuration_templates_deviceTemplates_attachDevices_Payload_POST_20.9.log
vmanage_rest_session/api_data/configuration_templates_deviceTemplates_attachDevices_devTP_Payload_POST_20.12.log
vmanage_rest_session/api_data/configuration_templates_deviceTemplates_attachDevices_getDeviceCsv_POST_20.9.log
vmanage_rest_session/api_data/configuration_templates_deviceTemplates_cliTemplate_LoadRunningConfigFromDevice_GET_20.9.log
vmanage_rest_session/api_data/configuration_templates_deviceTemplates_cliTemplate_deviceModule_GET_20.9.log
vmanage_rest_session/api_data/configuration_templates_deviceTemplates_getAllFeatureTemplate_GET_20.12.log
vmanage_rest_session/api_data/configuration_templates_deviceTemplates_getTemplate_GET_20.9.log
vmanage_rest_session/api_data/configuration_templates_deviceTemplates_statusGet_GET_20.9.log
vmanage_rest_session/api_data/getTemplateAttachStatus_configuration_templates_deviceTemplates_attachDevices_GET_20.9.log
vmanage_rest_session/api_data/monitor_devices_devices_devices_GET_20.11.log
vmanage_rest_session-1.0.8.dist-info/METADATA
vmanage_rest_session-1.0.8.dist-info/WHEEL
vmanage_rest_session-1.0.8.dist-info/top_level.txt
vmanage_rest_session-1.0.8.dist-info/zip-safe
vmanage_rest_session-1.0.8.dist-info/RECORD
