Metadata-Version: 2.1
Name: vmanage_rest_session
Version: 1.0.8
Summary: vmanage restapi session
Home-page: https://sdwan-git.cisco.com/crdc-tools/vmanage_rest_session
Author: demyang
Author-email: demyang@cisco.com
